magic_constants/__init__.py
magic_constants/metaconstant.py
magic_constants-1.0.0.dist-info/LICENSE
magic_constants-1.0.0.dist-info/METADATA
magic_constants-1.0.0.dist-info/WHEEL
magic_constants-1.0.0.dist-info/top_level.txt
magic_constants-1.0.0.dist-info/RECORD
