Metadata-Version: 2.1
Name: magic-constants
Version: 1.0.0
Summary: Make constants in python more magic 🪄
Author-email: Thomas Moll <tom@moll.dev>
Project-URL: Source, https://github.com/moll-dev/magic-constants
Project-URL: Issues, https://github.com/moll-dev/magic-constants/issues
Classifier: Programming Language :: Python :: 3
Requires-Python: >=3.10
License-File: LICENSE
Provides-Extra: test
Requires-Dist: pytest>=6; extra == "test"
